sublingual_eval.pth
sublingual_dashboard/__init__.py
sublingual_dashboard/cli.py
sublingual_dashboard/run_servers.py
sublingual_dashboard/server/api_routes.py
sublingual_dashboard/server/app.py
sublingual_dashboard/server/config.py
sublingual_dashboard/server/__pycache__/api_routes.cpython-312.pyc
sublingual_dashboard/server/__pycache__/config.cpython-312.pyc
sublingual_dashboard/server/evaluations/evaluation.py
sublingual_dashboard/server/evaluations/__pycache__/evaluation.cpython-312.pyc
sublingual_dashboard/server/frontend_build/favicon.ico
sublingual_dashboard/server/frontend_build/index.html
sublingual_dashboard/server/frontend_build/assets/index-B3VMVGlI.js
sublingual_dashboard/server/frontend_build/assets/index-B8klrcSS.js
sublingual_dashboard/server/frontend_build/assets/index-BhuISBHS.css
sublingual_dashboard/server/frontend_build/assets/index-C0nmAOqx.css
sublingual_dashboard/server/frontend_build/assets/index-C6i3hJzT.css
sublingual_dashboard/server/frontend_build/assets/index-D4nqI29e.css
sublingual_dashboard/server/frontend_build/assets/index-KF-c7Keh.js
sublingual_dashboard/server/frontend_build/assets/index-l27ko0aZ.js
sublingual_eval/__init__.py
sublingual_eval/initialization.py
sublingual_eval/site_customize.py
sublingual_eval/subl.py
sublingual_eval/wrapper_exec.py
sublingual_eval/wrapper_generic.py
sublingual_eval/abstract/__init__.py
sublingual_eval/abstract/grammar.py
sublingual_eval/abstract/utils.py
sublingual_eval/logging/__init__.py
sublingual_eval/logging/anthropic_logger.py
sublingual_eval/logging/django_logger.py
sublingual_eval/logging/fastapi_logger.py
sublingual_eval/logging/flask_logger.py
sublingual_eval/logging/openai_logger.py
subl-0.1.12.dist-info/METADATA
subl-0.1.12.dist-info/WHEEL
subl-0.1.12.dist-info/entry_points.txt
subl-0.1.12.dist-info/top_level.txt
subl-0.1.12.dist-info/RECORD
