Metadata-Version: 2.2
Name: subl
Version: 0.1.12
Summary: No-code LLM production app evals.
Home-page: https://github.com/sublingual-ai/sublingual
Author: Matthew Tang and Dylan Bowman
Author-email: founders@sublingual.ai
License: MIT
Requires-Python: >=3.10
Requires-Dist: flask
Requires-Dist: flask-cors
Requires-Dist: openai
Requires-Dist: dotenv
Requires-Dist: psutil
Requires-Dist: anthropic
Requires-Dist: posthog
Dynamic: author
Dynamic: author-email
Dynamic: home-page
Dynamic: license
Dynamic: requires-dist
Dynamic: requires-python
Dynamic: summary
